srsinst/qcm/__init__.py
srsinst/qcm/__main__.py
srsinst/qcm/qcm.taskconfig
srsinst/qcm/instruments/__init__.py
srsinst/qcm/instruments/get_instruments.py
srsinst/qcm/instruments/qcm200/__init__.py
srsinst/qcm/instruments/qcm200/commands.py
srsinst/qcm/instruments/qcm200/components.py
srsinst/qcm/instruments/qcm200/qcm.py
srsinst/qcm/tasks/qcmmonitortask.py
srsinst.qcm-0.1.0.dist-info/LICENSE.txt
srsinst.qcm-0.1.0.dist-info/METADATA
srsinst.qcm-0.1.0.dist-info/WHEEL
srsinst.qcm-0.1.0.dist-info/entry_points.txt
srsinst.qcm-0.1.0.dist-info/top_level.txt
srsinst.qcm-0.1.0.dist-info/RECORD
