Metadata-Version: 2.1
Name: srsinst.qcm
Version: 0.1.0
Summary: Instrument driver package for the Quartz Crystal Microbalance, QCM200 from Stanford Research Systems (SRS)
Author: Chulhoon Kim
License: MIT license
Keywords: QCM200,quartz crystal microbalanace,SRS,Stanford Research Systems
Classifier: Development Status :: 3 - Alpha
Classifier: Intended Audience :: Science/Research
Classifier: License :: OSI Approved :: MIT License
Classifier: Programming Language :: Python :: 3.7
Classifier: Programming Language :: Python :: 3.8
Classifier: Programming Language :: Python :: 3.9
Classifier: Programming Language :: Python :: 3.10
Classifier: Topic :: Scientific/Engineering
Classifier: Topic :: Scientific/Engineering :: Chemistry
Classifier: Topic :: Scientific/Engineering :: Physics
Requires-Python: >=3.7
License-File: LICENSE.txt
Requires-Dist: srsgui >=0.4.6
Provides-Extra: full
Requires-Dist: matplotlib >=3.6.2 ; extra == 'full'
Requires-Dist: pyside6 ; extra == 'full'
